{
  "name": "Charts",
  "version": "4.1.0",
  "summary": "Charts is a powerful & easy to use chart library for iOS, tvOS and OSX (and Android)",
  "homepage": "https://github.com/danielgindi/Charts",
  "license": {
    "type": "Apache License, Version 2.0",
    "file": "LICENSE"
  },
  "authors": [
    "Daniel Cohen Gindi",
    "Philipp Jahoda"
  ],
  "platforms": {
    "ios": "12.0"
  },
  "source": {
    "http": "http://localhost:8080/frameworks/Charts/4.1.0/zip",
    "type": "zip"
  },
  "swift_versions": "5.7",
  "cocoapods_version": ">= 1.5.0",
  "source_files": "bin_Charts_4.1.0/Headers/*",
  "public_header_files": "bin_Charts_4.1.0/Headers/*.h",
  "vendored_libraries": "bin_Charts_4.1.0/*.a",
  "description": "「   converted automatically by plugin cocoapods-bin  」",
  "swift_version": "5.7"
}
